agrotechsimapi/__init__.py
agrotechsimapi/client.py
agrotechsimapi/high_level_client.py
agrotechsimapi/pid.py
agrotechsimapi/signal_utils.py
agrotechsimapi/video_pb2.py
agrotechsimapi/video_pb2_grpc.py
agrotechsimapi/utils/__init__.py
agrotechsimapi/utils/aruco_marker_recognizer.py
agrotechsimapi/utils/recognition_setting.py
agrotechsimapi/utils/utils.py
agrotechsimapi/utils/vision.py
modules/camera_driver.py
modules/input_driver.py
modules/lidar_driver.py
agrotechsimapi-1.0.1.dist-info/METADATA
agrotechsimapi-1.0.1.dist-info/WHEEL
agrotechsimapi-1.0.1.dist-info/top_level.txt
agrotechsimapi-1.0.1.dist-info/RECORD
