Metadata-Version: 2.4
Name: agrotechsimapi
Version: 1.0.1
Summary: This repository contains the API for the AgroTechAvia simulators. This repository also contains several examples of how to interact with the API.
Author-email: AgroTechAvia <example@main.com>
License-Expression: Apache-2.0
Classifier: Programming Language :: Python :: 3
Classifier: Operating System :: OS Independent
Requires-Python: >=3.10
Requires-Dist: backports.ssl-match-hostname
Requires-Dist: contourpy
Requires-Dist: cycler
Requires-Dist: fonttools
Requires-Dist: future
Requires-Dist: grpcio
Requires-Dist: grpcio-tools
Requires-Dist: iso8601
Requires-Dist: kiwisolver
Requires-Dist: matplotlib
Requires-Dist: msgpack-python
Requires-Dist: msgpack-rpc-python
Requires-Dist: numpy
Requires-Dist: opencv-contrib-python
Requires-Dist: opencv-python
Requires-Dist: packaging
Requires-Dist: pillow
Requires-Dist: protobuf
Requires-Dist: pynput
Requires-Dist: pyparsing
Requires-Dist: python-dateutil
Requires-Dist: PyYAML
Requires-Dist: pyserial
Requires-Dist: six
Requires-Dist: tornado
Requires-Dist: transforms3d
Requires-Dist: inavmspapi
